{
  "A": {
    "_section_label": "A.? General Information",
    "A0": {
      "label": ". Respondent Informa on (Not for Publica on)",
      "raw_text": "A0. Respondent Informa on (Not for Publica on)\nName                 Cathleen Kisak\n\nTitle                Research Designer and Analyst\n\nO\ufb03ce                 Ins tu onal Research and Analysis\n\nMailing Address      5000 Forbes Avenue, UTDC Building, Pi sburgh, PA 15213\n\nPhone                412-268-7546\n\nFax                  N/A\n\nE-mail Address       ckisak@andrew.cmu.edu"
    },
    "A1": {
      "label": ". Address Informa on",
      "raw_text": "A1. Address Informa on\nName of College or University           Carnegie Mellon University\nMailing Address                         5000 Forbes Avenue, Pi sburgh, PA 15213\nStreet Address                          same as mailing address\nMain Phone Number                       412-268-2000\nWWW Home Page Address                   h p://www.cmu.edu\nAdmissions Phone Number                 412-268-2082\nAdmissions Toll-free Number\n\nAdmissions O\ufb03ce Mailing Address         Carnegie Mellon O\ufb03ce of Admission, 5000 Forbes Avenue, Pi sburgh, PA 15213\nAdmissions Fax Number                   412-268-7838\nAdmissions E-mail Address               admission@andrew.cmu.edu\nSeparate URL for online applica on:     admission.enrollment.cmu.edu/pages/apply-now"
    },
    "A2": {
      "label": ". Source of ins tu onal control:",
      "raw_text": "A2. Source of ins tu onal control:\n\n        Private (nonprofit)"
    },
    "A3": {
      "label": ". Classify your undergraduate ins tu on:",
      "raw_text": "A3. Classify your undergraduate ins tu on:\n\n        Coeduca onal college"
    },
    "A4": {
      "label": ". Academic year calendar:",
      "raw_text": "A4. Academic year calendar:\n\n        Semester"
    },
    "A5": {
      "label": ". Degrees o\ufb00ered by your ins tu on:",
      "raw_text": "A5. Degrees o\ufb00ered by your ins tu on:\n\n        Bachelor\u2019s                          Post-bachelor\u2019s cer ficate                      Master\u2019s\n\n        Post-master\u2019s cer ficate            Doctoral degree\u2014research/scholarship"
    },
    "A6": {
      "label": ". Diversity, Equity, and Inclusion Web Page:",
      "raw_text": "A6. Diversity, Equity, and Inclusion Web Page:\nh ps://www.cmu.edu/diversity/\n\n                                   CARNEGIE MELLON UNIVERSITY COMMON DATA SET 2024-2025\n                                                             2"
    }
  },
  "B": {
    "_section_label": "B.? ENROLLMENT AND PERSISTENCE",
    "B1": {
      "label": ". Ins tu onal Enrollment - Men and Women, as of October 15, 2024",
      "raw_text": " B1. Ins tu onal Enrollment - Men and Women, as of October 15, 2024\n\n\n\n\n                                                              FULL-TIME                                      PART-TIME\n\n                                                         Men        Women        Another       Un -     Men       Women      Another     Un -\n\n\nUndergraduates\n\nDegree-seeking, first- me first-year (Pi sburgh\n                                                         973          780             54           0         1          0       0          0\ncampus)\n\nDegree-seeking, first- me first-year (Doha campus)        55              63          0            0         0          0       0          0\nOther first-year, degree-seeking                          14               7          0            0         0          0       0          0\nAll other degree-seeking                                2,740       2,735         142              1     72        105          2          0\nTotal degree-seeking                                    3,782       3,585         196              1     73        105          2          0\nAll other undergraduates enrolled in credit courses           1            4           0           0     47          19         0          9\n\nTotal Undergraduates                                    3,783       3,589         196              1    120        124          2          9\n\n\n\n\n                                                          FULL-TIME                                      PART-TIME\n\n                                                       Men        Women        Another       Un -      Men       Women      Another      Un -\n                                                                                           reported                                    reported\n\nGraduate\n\nDegree-seeking, first- me                             1,907       1,332           1           25       123         70          0           3\nAll other degree-seeking                              2,955       1,718           4           27       343        159          0          12\nAll other graduates enrolled in credit courses          61          24            1            5        43         37          0           2\n\nTotal graduate                                        4,923       3,074           6           57       509        266          0          17\n\n\nTOTAL ALL STUDENTS                                    8,706       6,663         202           58       629        390          2          26\n\n\n\n\nTotal all undergraduates:                  Total all graduate:                             GRAND TOTAL ALL STUDENTS:\n                                   7,824                                         8,852                                                   16,676\n\n\n\n\n                                       CARNEGIE MELLON UNIVERSITY COMMON DATA SET 2024-2025\n                                                                 3"
    },
    "B2": {
      "label": ". Enrollment by Racial/Ethnic Category",
      "raw_text": "B2. Enrollment by Racial/Ethnic Category\n\n\n\n\n                                                             Degree-seeking            Degree-seeking                    Total\n                                                          First- me First-year,        Undergraduates                Undergraduates\n                                                            Pi sburgh Campus       (include first- me first-year),    (both degree\u2013 and\n                                                                                           All Campuses              non-degree-seeking),\n                                                                                                                        All Campuses\n\nInterna onal (nonresident )                                             362                             1,804                    1,823\nHispanic/La no                                                          115                               731                      735\nBlack or African-American, non-Hispanic                                  39                               292                      298\nWhite, non-Hispanic                                                     379                             1,587                    1,607\nAmerican Indian or Alaska Na ve, non-Hispanic                              0                                 1                        1\nAsian, non-Hispanic                                                     711                             2,524                    2,530\nNa ve Hawaiian or other Pacific Islander, non-Hispanic                     0                                 2                        2\nTwo or more races, non-Hispanic                                          75                               393                      394\nRace and/or ethnicity unknown                                           127                               410                      434\nTotal                                                                 1,808                             7,744                    7,824"
    },
    "B3": {
      "label": ". Number of degrees awarded by your ins tu on from July 1, 2023 to June 30, 2024",
      "raw_text": " B3. Number of degrees awarded by your ins tu on from July 1, 2023 to June 30, 2024\n\n\n\nCer ficate/diploma                                        Post-master\u2019s cer ficates                                                           5\n\nBachelor\u2019s degrees                              1,799     Doctoral degrees\u2014research/scholarship                                             346\nPostbachelor\u2019s cer ficates                        133     Doctoral degrees\u2014professional prac ce\nMaster\u2019s degrees                                3,534     Doctoral degrees\u2014other\n\n\n\n\n                                     CARNEGIE MELLON UNIVERSITY COMMON DATA SET 2024-2025\n                                                               4"
    },
    "B22": {
      "label": ". For the cohort of all full- me bachelor\u2019s (or equivalent) degree-seeking undergraduate students who",
      "raw_text": "B22. For the cohort of all full- me bachelor\u2019s (or equivalent) degree-seeking undergraduate students who\n     entered your ins tu on as freshmen in Fall 2023 (or the preceding summer term), what percentage\n                                                                                                                        98.0%\n     was enrolled at your ins tu on as of the date your ins tu on calculates its o\ufb03cial enrollment in Fall\n     2024? The ini al cohort may be adjusted for allowable exclusions.\n\n\n                                   CARNEGIE MELLON UNIVERSITY COMMON DATA SET 2024-2025\n                                                             5"
    }
  },
  "C": {
    "_section_label": "C.? FIRST-TIME,? FIRST-YEAR (?:\\(?FRESHMAN\\)? )?ADMISSION",
    "C1": {
      "label": ". First- me, first-year (freshman) students:",
      "raw_text": "C1. First- me, first-year (freshman) students:\nProvide the number of degree-seeking, first- me, first-year students who applied, were admi ed, and enrolled (full- or part- me)\nin Fall 2024. Include early decision, early ac on, and students who began studies during summer in this cohort. Applicants should\ninclude only those students who fulfilled the requirements for considera on for admission (i.e., who completed ac onable applica-\n  ons) and who have been no fied of one of the following ac ons: admission, non-admission, placement on wai ng list, or applica-\n  on withdrawn (by applicant or ins tu on). Admi ed applicants should include wait-listed students who were subsequently\no\ufb00ered admission. Since the total may include students who did not provide gender data, the detail need not sum to the total.\n\n\n\n\n                                                                   Men       Women          Another        Un -         Total\n\n\nTotal first- me, first-year (freshman) who applied:                20,143    12,735             1,063                    33,941\n\nTotal first- me, first-year (freshman) who were admi ed:             1,973     1,870             116                       3,959\n\nTotal full- me, first- me, first-year (freshman) who enrolled:        973        780              54                       1,807\n\nTotal part- me, first- me, first-year (freshman) who enrolled:          1          0               0                            1"
    },
    "C2": {
      "label": ". First- me, first-year (freshman) wait-listed students:",
      "raw_text": "C2. First- me, first-year (freshman) wait-listed students:\nStudents who met admission requirements but whose final admission was con ngent on space availability\n\nDo you have a policy of placing students on a wai ng list?                                Yes\nIf yes, please answer the ques ons below for Fall 2024 admissions:\n\nNumber of qualified applicants o\ufb00ered a place on wai ng list:                          16,484\n\nNumber of wait-listed students who accepted a place on the list:                       10,062\n\nNumber of wait-listed students admi ed:                                                   32\n\nIs your wai ng list ranked?                                                               No\n\nIf yes, do you release that informa on to students?                                      N/A\n\nDo you release that informa on to school counselors?                                     N/A\n\n\n\n\n                                 CARNEGIE MELLON UNIVERSITY COMMON DATA SET 2024-2025\n                                                           6"
    },
    "C3": {
      "label": ". High school comple on requirement",
      "raw_text": "C3. High school comple on requirement\nIden fy your high school comple on requirement for degree-seeking entering students:\n\nHigh school diploma is required and GED is accepted"
    },
    "C4": {
      "label": ". Does your ins tu on require or recommend a general college-preparatory program for degree-seeking students?",
      "raw_text": "C4. Does your ins tu on require or recommend a general college-preparatory program for degree-seeking students?\nRequire"
    },
    "C5": {
      "label": ". Distribu on of high school units required and/or recommended.",
      "raw_text": "C5. Distribu on of high school units required and/or recommended.\nSpecify the distribu on of academic high school course units required and/or recommended of all or most degree-seeking students\nusing Carnegie units (one unit equals one year of study or its equivalent). If you use a di\ufb00erent system for calcula ng units, please\nconvert.\n\n                                                                                         Units Required       Units Recommended\n\nTotal academic units*\n\nEnglish                                                                                           4                      4\n\nMathema cs                                                                                        4                      4\n\nScience                                                                                           3                      3\n\n  Of these, units that must be lab\n\nForeign language                                                                                  2                      2\n\nSocial studies\n\nHistory\n\nAcademic elec ves                                                                                 3                      3\n\nComputer science\n\nVisual/Performing arts\n\nOther\n\n*Average requirements stated above. Requirements vary by program\u2014please see CMU admissions website for program-specific\n requirements\u2014www.cmu.edu/admission/admission\n\n\nBasis for Selec on"
    },
    "C6": {
      "label": ". Do you have an open admission policy, under which virtually all secondary school graduates or students with",
      "raw_text": "C6. Do you have an open admission policy, under which virtually all secondary school graduates or students with\n   GED equivalency diplomas are admi ed without regard to academic record, test scores, or other qualifica ons?\n\n   No\n\n\n\n                                 CARNEGIE MELLON UNIVERSITY COMMON DATA SET 2024-2025\n                                                           7"
    },
    "C7": {
      "label": ". Rela ve importance of each of the following academic and nonacademic factors in your first- me, first-year,",
      "raw_text": "C7. Rela ve importance of each of the following academic and nonacademic factors in your first- me, first-year,\n    degree-seeking (freshmen) admission decisions.\n\n                                               Very important     Important       Considered       Not considered\n\nAcademic\n\n  Rigor of secondary school record                   X\n\n  Class rank                                         X\n\n  Academic GPA                                       X\n\n  Standardized test scores                                                             X\n\n  Applica on essay                                                    X\n\n  Recommenda on(s)                                                    X\n\nNonacademic\n\n  Interview                                                                                               X\n\n  Extracurricular ac vi es                           X\n\n  Talent/ability                                                      X\n\n  Character/personal quali es                        X\n\n  First genera on                                                     X\n\n  Alumni/ae rela on                                                                                       X\n\n  Geographical residence                                                               X\n\n  State residency                                                                                         X\n\n  Religious a\ufb03lia on/commitment                                                                           X\n\n  Volunteer work                                     X\n\n  Work experience                                                                      X\n\n  Level of applicant interest                                                                             X\n\n\n\n\nPlease provide addi onal informa on if the importance of any specific academic or nonacademic factors di\ufb00er by\nacademic program.\n\n\n                                CARNEGIE MELLON UNIVERSITY COMMON DATA SET 2024-2025\n                                                          8"
    },
    "C8": {
      "label": ". Entrance exams",
      "raw_text": "C8. Entrance exams\nA. Does your ins tu on make use of SAT, ACT, or SAT Subject Test scores in admission decisions for first- me, first-year, degree-\n   seeking applicants? Yes\n\n     Reflect your ins tu on\u2019s policies for use in admission for Fall 2024.\n\n                                                    Require       Recommend             Require          Consider if          Not\n                                                                                       for Some          Submi ed          Considered\n\nSAT or ACT                                                                                                    X\nACT only\nSAT only\n\n\n\n\n                                                                                           SAT essay                   ACT essay\nFor admission\nFor placement\nFor advising\nIn place of an applica on essay\nAs a validity check on the applica on essay\nNo college policy as of now\nNot using essay component                                                                      X                           X\n\n\n\nD. In addi on, does your ins tu on use applicants\u2019 test scores for academic advising? No\n\n\nE.   Latest date by which SAT or ACT scores must be received for fall-term admission: January 1\n\n     Latest date by which SAT Subject Test scores must be received for fall-term admission: January 1\n\n\nF.   If necessary, use this space to clarify your test policies (e.g., if tests are recommended for some students, or if tests are not\n     required of some students):\n\n\n\n\nG.    Please indicate which tests your ins tu on uses for placement (e.g., state tests):\n\n\n           SAT                                                X AP\n           ACT                                                  CLEP\n           SAT subject tests                                    Ins tu onal exam\n\n\n                                   CARNEGIE MELLON UNIVERSITY COMMON DATA SET 2024-2025\n                                                             9"
    },
    "C9": {
      "label": ". Percent and number of first- me, first-year (freshman) students enrolled in Fall 2024 who submi ed na onal",
      "raw_text": " C9. Percent and number of first- me, first-year (freshman) students enrolled in Fall 2024 who submi ed na onal\n standardized (SAT/ACT) test scores. Include informa on for all enrolled, degree-seeking, first- me, first-year\n (freshman) students who submi ed their test scores.\n\n        Percent Submi ng         Number Submi ng\n SAT            52.6%                   951\n ACT            22.4%                   405\n\n\n\n\n                                              25th Percen le       50th Percen le              75th Percen le\nSAT Composite                                     1510                 1540                         1560\nSAT Evidence-based Reading and                     730                  750                          770\nWri ng\nSAT Math                                           770                  790                          800\n\n\nACT Composite                                      34                   35                           35\nACT Math                                           34                   35                           36\nACT English                                        33                   35                           36\nACT Wri ng\nACT Science\nACT Reading\n\n\n\n                                                                                Ques on C9 is con nued on the next page\n\n\n\n\n                                 CARNEGIE MELLON UNIVERSITY COMMON DATA SET 2024-2025\n                                                          10\nC9 (con nued). Percent and number of first- me, first-year (freshman) students enrolled in Fall 2024 who submi ed\nna onal standardized (SAT/ACT) test scores. Include informa on for all enrolled, degree-seeking, first- me, first-\nyear (freshman) students who submi ed their test scores.\n\n\nPercent of first- me, first-year (freshman) students with scores in each range:\n\n\n                                         SAT Composite\n\n\n1400-1600                                    96.32%\n1200-1399                                     3.47%\n1000-1199                                     0.11%\n800-999                                       0.11%\n600-799                                       0.00%\n400-599                                       0.00%\n\n\n\n\n                                  SAT Evidence-based Reading                  SAT Math         SAT Wri ng\n\n\n700-800                                      92.23%                               95.79%\n600-699                                       7.68%                               3.58%\n500-599                                       0.09%                               0.53%\n400-499                                       0.00%                               0.11%\n300-399                                       0.09%                               0.00%\n200-299                                       0.00%                               0.00%\n\n\n\n\n                                         ACT Composite                       ACT English       ACT Math\n\n30-36                                        97.78%                               97.0%          93.73%\n24-29                                         2.22%                               2.45%          5.72%\n18-23                                         0.00%                               0.55%          0.55%\n12-17                                         0.00%                               0.00%          0.00%\n6-11                                          0.00%                               0.00%          0.00%\nBelow 6                                       0.00%                               0.00%          0.00%\n\n\n\n\n                                 CARNEGIE MELLON UNIVERSITY COMMON DATA SET 2024-2025\n                                                          11"
    },
    "C10": {
      "label": ". Percent of all degree-seeking, first- me, first-year (freshman) students who had high school class rank within",
      "raw_text": "C10. Percent of all degree-seeking, first- me, first-year (freshman) students who had high school class rank within\n     each of the following ranges (report informa on for those students from whom you collected high school rank\n     informa on).\nPercent in top tenth of high school gradua ng class                            96.8%\nPercent in top quarter of high school gradua ng class                          99.8%\nPercent in top half of high school gradua ng class                             99.8%\n                                                                                           Top half + bo om half = 100%\nPercent in bo om half of high school gradua ng class                           0.2%\nPercent in bo om quarter of high school gradua ng class                        0.1%\nPercent of total first- me, first-year (freshman) students who submi ed        98.2%\nhigh school class rank:"
    },
    "C11": {
      "label": ". Percentage of all enrolled, degree-seeking, first- me, first-year (freshman) students who had high school grade-",
      "raw_text": "C11. Percentage of all enrolled, degree-seeking, first- me, first-year (freshman) students who had high school grade-\n     point averages within each of the following ranges (using 4.0 scale). Report informa on only for those students\n     from whom you collected high school GPA.\nPercent who had GPA of 4.0                                        46.9%\nPercent who had GPA of between 3.75 and 3.99                      38.3%\nPercent who had GPA between 3.50 and 3.74                         11.3%\nPercent who had GPA between 3.25 and 3.49                           2.6%\nPercent who had GPA between 3.00 and 3.24                           0.3%\nPercent who had GPA between 2.50 and 2.99                           0.4%\nPercent who had GPA between 2.0 and 2.49                          0.06%\nPercent who had GPA between 1.0 and 1.99                          0.06%\nPercent who had GPA below 1.0                                       0.0%"
    },
    "C12": {
      "label": ". High school GPA of all degree-seeking, first- me, first-year (freshman) students:",
      "raw_text": "C12. High school GPA of all degree-seeking, first- me, first-year (freshman) students:\n\nAverage high school GPA of all degree-seeking, first- me, first-year (freshman) students who submi ed GPA                 3.89\nPercent of total first- me, first-year (freshman) students who submi ed high school GPA:                                  98.0%\n\n\nAdmission Policies"
    },
    "C13": {
      "label": ". Applica on fee",
      "raw_text": "C13. Applica on fee\nDoes your ins tu on have an applica on fee? Yes\n\nAmount of applica on fee: $75\n\nCan it be waived for applicants with financial need? Yes\n\nIf you have an applica on fee and an on-line applica on op on, please indicate policy for students who apply online: Same fee\n\nCan on-line applica on fee be waived for applicants with financial need? Yes\n\n\n\n                                  CARNEGIE MELLON UNIVERSITY COMMON DATA SET 2024-2025\n                                                           12"
    },
    "C14": {
      "label": ". Applica on closing date",
      "raw_text": "C14. Applica on closing date\nDoes your ins tu on have an applica on closing date? Yes\n\nApplica on closing date (fall): January 1 (December 1 for Drama and Music)\n\nPriority date:"
    },
    "C15": {
      "label": ". Are first- me, first-year students accepted for terms other than the fall? No",
      "raw_text": "C15. Are first- me, first-year students accepted for terms other than the fall? No"
    },
    "C16": {
      "label": ". No fica on to applicants of admission decision sent: By April 1",
      "raw_text": "C16. No fica on to applicants of admission decision sent: By April 1"
    },
    "C17": {
      "label": ". Reply policy for admi ed applicants",
      "raw_text": "C17. Reply policy for admi ed applicants\nMust reply by May 1\n\nHousing deposit deadline and amount: May 31 \u2014 $800 (not refundable if student does not enroll)"
    },
    "C18": {
      "label": ". Deferred admission",
      "raw_text": "C18. Deferred admission\nDoes your ins tu on allow students to postpone enrollment a er admission? Yes\n\nIf yes, maximum period of postponement? Two years"
    },
    "C19": {
      "label": ". Early admission of high school students:",
      "raw_text": "C19. Early admission of high school students:\nDoes your ins tu on allow high school students to enroll as full- me, first- me, first-year (freshman) students one year or more\nbefore high school gradua on? Yes\n\nEarly Decision and Early Ac on Plans"
    },
    "C21": {
      "label": ". Early decision:",
      "raw_text": "C21. Early decision:\nDoes your ins tu on o\ufb00er an early decision plan (an admission plan that permits students to apply and be no fied of an admission\ndecision well in advance of the regular no fica on date and that asks students to commit to a ending if accepted) for first- me,\nfirst-year (freshman) applicants for fall enrollment? Yes\n\n\nFirst or only early decision plan closing date:      November 1 (not available for Ac ng, Direc ng, Dramaturgy, Music Theater,\n                                                                  or School of Music)\nFirst or only early decision plan no fica on date:   December 15 (admi ed applicants must reply by February 1)\n\nOther early decision plan closing date:\nOther early decision plan no fica on date:\n\n\nFor the Fall 2024 entering class:\n\nNumber of early decision applica ons received by your ins tu on:     4,423\n\nNumber of applicants admi ed under early decision plan:                612"
    },
    "C22": {
      "label": ". Early ac on:",
      "raw_text": "C22. Early ac on:\nDo you have a nonbinding early ac on plan whereby students are no fied of an admission decision well in advance of the regular\nno fica on date but do not have to commit to a ending your college? No\n\n\n                                    CARNEGIE MELLON UNIVERSITY COMMON DATA SET 2024-2025\n                                                             13"
    }
  },
  "D": {
    "_section_label": "D.? TRANSFER ADMISSION",
    "D1": {
      "label": ". Does your ins tu on enroll transfer students?",
      "raw_text": "D1. Does your ins tu on enroll transfer students?\nYes\n- If yes, may transfer students earn advanced standing credit by transferring credits from course work completed at\n  other colleges/universi es? Yes"
    },
    "D2": {
      "label": ". Provide the number of students who applied, were admi ed, and enrolled as degree-seeking transfer students",
      "raw_text": "D2. Provide the number of students who applied, were admi ed, and enrolled as degree-seeking transfer students\n    in Fall 2024.\n                                            Applicants                  Admi ed Applicants                Enrolled Applicants\nMen                                           1,084                              52                               21\nWomen                                          540                               41                               15\nAnother Gender                                  64                                1                                1\n\nTotal                                         1,688                              94                               37\nApplica on for Admission"
    },
    "D3": {
      "label": ". Indicate terms for which transfers may enroll:",
      "raw_text": "D3. Indicate terms for which transfers may enroll:\nFall, Spring (depending on college)"
    },
    "D4": {
      "label": ". Must a transfer applicant have a minimum number of credits completed or else must apply as an entering",
      "raw_text": "D4. Must a transfer applicant have a minimum number of credits completed or else must apply as an entering\n    freshman?\nNo"
    },
    "D5": {
      "label": ". Indicate all items required of transfer students to apply for admission:",
      "raw_text": "D5. Indicate all items required of transfer students to apply for admission:\n                                                            Required    Recommended        Recommended       Required       Not\n                                                             of All         of All            of Some        of Some      Required\n\nHigh school transcript                                          X\nCollege transcript(s)                                           X\nEssay or personal statement                                     X\nInterview                                                                                                                       X\nStandardized test scores                                                                                                        X\nStatement of good standing from prior ins tu on(s)                                                                              X"
    },
    "D6": {
      "label": ". If a minimum high school grade point average is required of transfer applicants, specify (on a 4.0 scale):",
      "raw_text": "D6. If a minimum high school grade point average is required of transfer applicants, specify (on a 4.0 scale):"
    },
    "D7": {
      "label": ". If a minimum college grade point average is required of transfer applicants, specify (on a 4.0 scale):",
      "raw_text": "D7. If a minimum college grade point average is required of transfer applicants, specify (on a 4.0 scale):"
    },
    "D8": {
      "label": ". List any other applica on requirements specific to transfer applicants:",
      "raw_text": "D8. List any other applica on requirements specific to transfer applicants:\nTransfer applicants must submit a college transcript in addi on to a high school transcript, and email a copy of course descrip ons\nfrom a college catalog from each college/university a ended. A recommenda on from a professor or advisor should be submi ed\nin place of a college counselor recommenda on. The College Report (a Common Applica on form) is also required from the\ncurrent academic ins tu on.\n\n                                  CARNEGIE MELLON UNIVERSITY COMMON DATA SET 2024-2025\n                                                           14"
    },
    "D9": {
      "label": ". List applica on priority, closing, no fica on, and candidate reply dates for transfer students. If applica ons are",
      "raw_text": "D9. List applica on priority, closing, no fica on, and candidate reply dates for transfer students. If applica ons are\n    reviewed on a con nuous or rolling basis, place a check mark in the \u201cRolling admission\u201d column.\n\n\n                          Priority Date         Closing Date        No fica on Date          Reply Date        Rolling Admission\nFall                                         February 15            May 15 (April 15 for June 1 (May 1 for\n                                             (December 1 for        CFA)                 CFA)\n                                             performing arts;\n                                             January 1 for visual\n                                             arts)\nWinter\nSpring                                       October 15             December 15          January 1\n\nSummer"
    },
    "D10": {
      "label": ". Does an open admission policy, if reported, apply to transfer students?",
      "raw_text": "D10. Does an open admission policy, if reported, apply to transfer students?"
    },
    "D11": {
      "label": ". Describe addi onal requirements for transfer admission, if applicable:",
      "raw_text": "D11. Describe addi onal requirements for transfer admission, if applicable:\nTransfer applicants must submit a college transcript in addi on to a high school transcript and email a copy of course descrip ons\nfrom a college catalog from each college/university a ended. A recommenda on from a professor or advisor should be submi ed\nin place of a college counselor recommenda on. The College Report (a Common Applica on form) is also required from the cur-\nrent academic ins tu on.\n\nTransfer Credit Policies"
    },
    "D12": {
      "label": ". Report the lowest grade earned for any course that may be transferred for credit:",
      "raw_text": " D12. Report the lowest grade earned for any course that may be transferred for credit:"
    },
    "D13": {
      "label": ". Maximum number of credits that transfers must complete at your ins tu on to earn an associate degree:",
      "raw_text": "D13. Maximum number of credits that transfers must complete at your ins tu on to earn an associate degree:"
    },
    "D14": {
      "label": ". Maximum number of credits that transfers must complete at your ins tu on to earn a bachelor\u2019s degree:",
      "raw_text": "D14. Maximum number of credits that transfers must complete at your ins tu on to earn a bachelor\u2019s degree:"
    },
    "D15": {
      "label": ". Minimum number of credits that transfers must complete at your ins tu on to earn an associate degree:",
      "raw_text": "D15. Minimum number of credits that transfers must complete at your ins tu on to earn an associate degree:"
    },
    "D16": {
      "label": ". Minimum number of credits that transfers must complete at your ins tu on to earn a bachelor\u2019s degree:",
      "raw_text": "D16. Minimum number of credits that transfers must complete at your ins tu on to earn a bachelor\u2019s degree:"
    },
    "D17": {
      "label": ". Describe other transfer credit policies:",
      "raw_text": "D17. Describe other transfer credit policies:\n\nTransfer credit evaluated on an individual basis and varies by college.\n\n\n\n\n                                  CARNEGIE MELLON UNIVERSITY COMMON DATA SET 2024-2025\n                                                           15"
    },
    "D18": {
      "label": ". Does your ins tu on accept the following military/veteran transfer credits:",
      "raw_text": "D18. Does your ins tu on accept the following military/veteran transfer credits:\n\n                                                                                     Yes       No\nAmerican Council on Educa on (ACE)                                                             X\n\nCollege Level Examina on Program (CLEP)                                                        X\n\nDANTES Subject Standardized Tests (DSST)                                                       X"
    },
    "D19": {
      "label": ".",
      "raw_text": "D19.\n\n                                                                                   Number   Unit Type\nMaximum number of credits or courses that may be transferred based on mili-          N/A      N/A\ntary educa on evaluated by the American Council on Educa on (ACE)"
    },
    "D20": {
      "label": ".",
      "raw_text": "D20.\n\n                                                                                   Number   Unit Type\nMaximum number of credits or courses that may be transferred based on De-            N/A      N/A\npartment of Defense supported prior learning assessments (College Level Ex-\namina on Program (CLEP) or DANTES Subject Standardized Tests (DSST)):"
    },
    "D21": {
      "label": ".",
      "raw_text": "D21.\n\n                                                                                     Yes       No\nAre the military/veteran credit transfer policies published on your website?          X\nIf yes, please provide the URL where the policy can be located:\n\nIf yes, please provide the URL where the policy can be located:\n\nh ps://www.cmu.edu/hub/registrar/veterans-benefits/"
    },
    "D22": {
      "label": ". Describe other military/veteran transfer credit policies unique to your ins tu on:",
      "raw_text": "D22. Describe other military/veteran transfer credit policies unique to your ins tu on:\n\n\n\n\n                              CARNEGIE MELLON UNIVERSITY COMMON DATA SET 2024-2025\n                                                       16"
    }
  },
  "E": {
    "_section_label": "E.? ACADEMIC OFFERINGS AND POLICIES",
    "E1": {
      "label": ". Special study op ons: Iden fy those programs available at your ins tu on. Refer to the glossary for defini ons.",
      "raw_text": "   E1. Special study op ons: Iden fy those programs available at your ins tu on. Refer to the glossary for defini ons.\n\n    X   Accelerated Program                                              X   Independent study\n    X   Comprehensive transi on and postsecondary program                X   Internships\n        for students with intellectual disabili es\n    X   Cross-registra on                                                X   Liberal arts/career combina on\n    X   Distance learning                                                X   Student-designed major\n    X   Double major                                                     X   Study abroad\n    X   Dual enrollment                                                  X   Teacher cer fica on program\n        English as a Second Language (ESL)                               X   Undergraduate Research\n        Exchange student program (domes c)                                   Weekend college\n        External degree program                                              Other\n        Honors program"
    },
    "E3": {
      "label": ". Areas in which all or most students are required to complete some course work prior to gradua on:",
      "raw_text": " E3. Areas in which all or most students are required to complete some course work prior to gradua on:\n\n\n\n                 Arts/fine arts                                  Intensive wri ng\n             X Computer literacy                                 Mathema cs\n                 English (including composi on)                  Philosophy\n\n                 Foreign languages                               Sciences (biological or physical)\n                 History                                         Social science\n                 Physical Educa on                             X Other\n                 Humani es\n\n\n\n\nRequirements vary considerably across colleges and programs.\n\n\n\n\n                                   CARNEGIE MELLON UNIVERSITY COMMON DATA SET 2024-2025\n                                                            17"
    }
  },
  "F": {
    "_section_label": "F.? STUDENT LIFE",
    "F1": {
      "label": ". Percentages of first- me, full- me (freshman) degree-seeking students and degree-seeking undergraduates",
      "raw_text": "F1. Percentages of first- me, full- me (freshman) degree-seeking students and degree-seeking undergraduates\n    enrolled in Fall 2024 who fit the following categories:\n\n                                                                             First- me, first-year   Undergraduates\n                                                                             (freshman) students\nPercent who are from out of state (exclude interna onal/nonresident aliens           88.4%                86.4%\nfrom the numerator and denominator)\nPercent of men who join fraterni es                                                                       6.9%\nPercent of women who join sorori es                                                                       6.8%\nPercent who live in college-owned, -operated, or \u2013a\ufb03liated housing                   99.9%                51.5%\nPercent who live o\ufb00 campus or commute                                                0.0%                 48.5%\nPercent of students age 25 and older                                                 0.0%                 25.8%\nAverage age of full- me students                                                     18.05                19.66\nAverage age of all students (full- and part- me)                                     18.05                19.71"
    },
    "F2": {
      "label": ". Ac vi es o\ufb00ered:",
      "raw_text": "F2. Ac vi es o\ufb00ered:\n\n      X Campus Ministries                          X Literary magazine            X Radio sta on\n\n\n      X Choral groups                              X Marching band                X Student government\n\n\n      X Concert band                               X Model UN                     X Student newspaper\n\n\n      X Dance                                      X Music ensembles              X Student-run film society\n\n\n      X Drama/theater                              X Musical theater              X Symphony orchestra\n\n\n      X Interna onal student organiza on           X Opera                            Television sta on\n\n\n      X Jazz band                                  X Pep band                     X Yearbook\n\n\n\n\n                              CARNEGIE MELLON UNIVERSITY COMMON DATA SET 2024-2025\n                                                       18"
    },
    "F3": {
      "label": ". ROTC (program o\ufb00ered in coopera on with Reserve O\ufb03cers\u2019 Training Corps)",
      "raw_text": "F3. ROTC (program o\ufb00ered in coopera on with Reserve O\ufb03cers\u2019 Training Corps)\nArmy ROTC is o\ufb00ered:\n                                   On campus\n\n\n                               X   At coopera ng ins tu on (name): University of Pi sburgh\n\n\nNaval ROTC is o\ufb00ered:\n  Marine Op on is o\ufb00ered:      X\n\n\n                               X   On campus\n\n\n                                   At coopera ng ins tu on (name):\n\n\nAir Force ROTC is o\ufb00ered:\n                                   On campus\n\n\n                               X   At coopera ng ins tu on (name): University of Pi sburgh"
    },
    "F4": {
      "label": ". Housing: check all types of college-owned, -operated, or \u2013a\ufb03liated housing available for your undergraduates at",
      "raw_text": "F4. Housing: check all types of college-owned, -operated, or \u2013a\ufb03liated housing available for your undergraduates at\n    your ins tu on.\n\n\n       X Coed dorms                                      X Special housing for disabled students\n\n\n       X Men\u2019s dorms                                        Special housing for interna onal students\n\n\n       X Women\u2019s dorms                                   X Fraternity/sorority housing\n\n\n           Apartments for married students                  Coopera ve housing\n\n\n       X Apartments for single students                  X Theme housing\n\n\n       X Wellness housing                                   Other housing op ons (specify):\n\n\n           Living Learning Communi es\n\n\n\n\n                             CARNEGIE MELLON UNIVERSITY COMMON DATA SET 2024-2025\n                                                      19"
    }
  },
  "G": {
    "_section_label": "G.? (?:ANNUAL EXPENSES|ANNUAL EXPENSE)",
    "G0": {
      "label": ". Please provide the URL of your ins tu on\u2019s net price calculator:",
      "raw_text": "G0. Please provide the URL of your ins tu on\u2019s net price calculator:\nh ps://admission.enrollment.cmu.edu/pages/net-price-calculator\n\nProvide 2025-2026 academic year costs of a endance for the following categories that are applicable to your ins tu-\n on:"
    },
    "G1": {
      "label": ". Undergraduate full- me tui on, required fees, room and board",
      "raw_text": "G1. Undergraduate full- me tui on, required fees, room and board\nList the typical tui on, required fees, and room and board for a full- me undergraduate student for the FULL 2025-\n2026 academic year. A full academic year refers to the period of me generally extending from September to June;\nusually equated to two semesters, two trimesters, three quarters, or the period covered by a four-one-four plan. Room\nand board is defined as double occupancy and 19 meals per week or the maximum meal plan. Required fees include\nonly charges that all full- me students must pay that are not included in tui on (e.g., registra on, health, or ac vity\nfees.) Do not include op onal fees (e.g., parking, laboratory use).\n\n\n                                  FIRST-YEAR          UNDERGRADUATES\nPRIVATE INSTITUTION                 $67,020                 $67,020\nTui on:\nREQUIRED FEES:                      $1,756                   $1,076\nROOM AND BOARD:                     $18,894                 $21,698\n(on-campus)\n\nROOM ONLY:                          $11,250                 $14,364\n(on-campus)\nBOARD ONLY:                         $7,644                   $7,334\n(on-campus meal plan)\n\n    First-year Experience Fee $680, Transporta on Fee $282, Technology Fee $480\n    Ac vity Fee $314 (Ac vity Fee is assessed by Student Government)"
    },
    "G2": {
      "label": ". Number of credits per term a student can take for the states full- me tui on: _____minimum _____maximum",
      "raw_text": "G2. Number of credits per term a student can take for the states full- me tui on: _____minimum _____maximum"
    },
    "G3": {
      "label": ". Do tui on and fees vary by year of study (e.g., sophomore, junior, senior)?        Yes        X No",
      "raw_text": "G3. Do tui on and fees vary by year of study (e.g., sophomore, junior, senior)?        Yes        X No"
    },
    "G4": {
      "label": ". Do tui on and fees vary by undergraduate instruc onal program?             Yes     X     No",
      "raw_text": "G4. Do tui on and fees vary by undergraduate instruc onal program?             Yes     X     No\nIf yes, what percentage of full- me undergraduates pay more than the tui on and fees reported in G1?\n\n\n\n\n                               CARNEGIE MELLON UNIVERSITY COMMON DATA SET 2024-2025\n                                                        20"
    },
    "G5": {
      "label": ". Provide the es mated expenses for a typical full- me undergraduate student:",
      "raw_text": "G5. Provide the es mated expenses for a typical full- me undergraduate student:\n\n                                                          Residents         Commuters           Commuters\n                                                                         (living at home)   (not living at home)\nBooks and supplies                                         $1,000            $1,000               $1,000\n\nRoom only                                                                                         $9,750\n\nBoard only                                                                   $3,822               $7,334\n\nRoom and board total (if your college cannot provide\nseparate room and board figures for commuters not liv-\ning at home):\nTransporta on (Varies significantly for residents and           $0            $680                  $0\ncommuters not living at home based on home state.)\nOther expenses                                             $1,400            $1,400               $1,400"
    },
    "G6": {
      "label": ". Undergraduate per-credit-hour charges (tui on only): $931",
      "raw_text": "G6. Undergraduate per-credit-hour charges (tui on only): $931\n\nPRIVATE INSTITUTIONS:\n\n\n\n\n                              CARNEGIE MELLON UNIVERSITY COMMON DATA SET 2024-2025\n                                                       21"
    }
  },
  "H": {
    "_section_label": "H.? FINANCIAL AID",
    "H1": {
      "label": ". Enter total dollar amounts awarded to enrolled full- me and less than full- me degree-seeking undergraduates",
      "raw_text": "H1. Enter total dollar amounts awarded to enrolled full- me and less than full- me degree-seeking undergraduates\n    in the following categories. Include aid awarded to interna onal students (i.e., those not qualifying for federal\n    aid). Aid that is non-need-based but that was used to meet need should be reported in the need-based aid\n    column.\n\nIndicate the academic year for which data are reported for items H1, H2, H2A, and H6: 2024-2025 es mated\nWhich needs-analysis methodology does your ins tu on use in awarding ins tu onal aid?\n       Federal methodology (FM)\n\n\n       Ins tu onal methodology (IM)\n\n\n   X   Both FM and IM\n\n\n\n                                                                                       Need based $ Non need based\n                                                                                                          $\nScholarships/Grants\n\n Federal                                                                                $10,753,366                     0\n State (all states, not only the state in which your ins tu on is located)                 $927,236                     0\n Ins tu onal: Endowed scholarships, annual gi s and tui on-funded grants, awarded      $152,561,532        $3,775,528\n by the college, excluding athle c aid and tui on waivers (which are reported below)\n Scholarships/grants from external sources (e.g., Kiwanis, Na onal Merit) not            $1,900,192        $2,794,692\n awarded by the college\nTOTAL Scholarships/Grants                                                              $166,142,326        $6,570,220\n\n\n\nSelf-Help\n Student loans from all sources (excluding parent loans)                                 $9,648,337        $9,394,053\n Federal Work-Study                                                                      $5,959,976\n State and other (e.g., ins tu onal) work-study/employment (Note: Excludes                        $0                $0\n Federal Work Study captured above.)\nTOTAL Self-Help                                                                         $15,608,313        $9,394,053\n\n\n\nParent Loans                                                                               $115,373       $10,624,519\nTui on Waivers                                                                             $859,344        $8,082,446\nAthle c Awards                                                                                     0                    0\n\n\n                               CARNEGIE MELLON UNIVERSITY COMMON DATA SET 2024-2025\n                                                        22"
    },
    "H2": {
      "label": ". Number of Enrolled Students Awarded Aid: List the number of degree-seeking full- me and less-than-full- me",
      "raw_text": "H2. Number of Enrolled Students Awarded Aid: List the number of degree-seeking full- me and less-than-full- me\n    undergraduates who applied for and were awarded financial aid from any source. Aid that is non-need-based\n    but that was used to meet need should be counted as need-based aid. Numbers should reflect the cohort\n    awarded the dollars reported in H1. Note: In the chart below, students may be counted in more than one row,\n    and full- me freshmen should also be counted as full- me undergraduates.\n\n                                                                       First- me, Full- Full- me Under- Less Than Full-\n                                                                         me Freshmen, grad (Incl. Fresh), me Undergrad,\n                                                                       Pi sburgh        All Campuses      All Campuses\n                                                                       Campus\nA. Number of degree-seeking undergraduate students (CDS Item               1,807            7,564             180\n   B1 if repor ng on Fall 2024 cohort)\n\nB. Number of students in line A who applied for need-based finan-           990             3,472             39\n   cial aid\n\nC. Number of students in line B who were determined to have                 649             2,988             31\n   financial need\nD. Number of students in line C who were awarded any                        649             2,986             31\n   financial aid\nE. Number of students in line D who were awarded any need-                  603             2,881             27\n   based scholarship or grant aid\nF.   Number of students in line D who were awarded any need-                540             2,440             26\n     based self-help aid\nG. Number of students in line D who were awarded any non-                    48              225               3\n   need-based scholarship or grant aid\nH. Number of students in line D whose need was fully met                    641             2,784             31\n   (exclude PLUS loans, unsubsidized loans, and private\n   alterna ve loans)\nI.   On average, the percentage of need that was met of                    100.0%          100.0%           100.0%\n     students who were awarded any need-based aid. Exclude any\n     aid that was awarded in excess of need as well as any resources\n     that were awarded to replace EFC (PLUS loans, unsubsidized\n     loans, and private alterna ve loans)\nJ. The average financial aid package of those in line D. Exclude any      $56,005          $60,909          $39,699\n   resources that were awarded to replace EFC (PLUS loans, un-\n   subsidized loans, and private alterna ve loans)\nK. Average need-based scholarship or grant award of those in line         $56,222          $57,941          $39,579\n   E\nL. Average need-based self-help award (excluding PLUS loans, un-           $4,564          $6,333           $6,232\n   subsidized loans, and private alterna ve loans) of those in line\n   F\nM. Average need-based loan (excluding PLUS loans, unsubsidized             $3,080          $4,108           $4,319\n   loans, and private alterna ve loans) of those in line F who were\n   awarded a need-based loan\n                                CARNEGIE MELLON UNIVERSITY COMMON DATA SET 2024-2025\n                                                         23"
    },
    "H4": {
      "label": "and H5",
      "raw_text": "H4 and H5\n  Include:\n   \u2022 2024 undergraduate class: all students who started at Carnegie Mellon University as first- me students and\n     received a bachelor\u2019s degree between July 1, 2024 and June 30, 2025\n      \u2022 only loans made to students who borrowed while enrolled at Carnegie Mellon University\n      \u2022 co-signed loans\n\n   Exclude:\n    \u2022 students who transferred in\n      \u2022 money borrowed at other ins tu ons\n      \u2022 parent loans\n      \u2022 students who did not graduate or who graduated with another degree or cer ficate (but no bachelor\u2019s degree)\nH4.\nProvide the number of students in the 2024 undergraduate class who started at your ins tu on as        1,712\nfirst- me students and received a bachelor\u2019s degree between July 1, 2023 and June 30, 2024.\nExclude students who transferred into your ins tu on.\n\n\n\n\n                               CARNEGIE MELLON UNIVERSITY COMMON DATA SET 2024-2025\n                                                        24"
    },
    "H5": {
      "label": ". Number and percent of students in class (defined in H4 above) borrowing from federal, non-federal, and any",
      "raw_text": "H5. Number and percent of students in class (defined in H4 above) borrowing from federal, non-federal, and any\nloan sources, and the average (or mean) amount borrowed:\n\n                                                                     Number in the    Percent of the   Average per-\n                                                                     class (defined   class (defined   undergraduate-\n                                                                     in H4 above)     in H4 above)     borrower cumula-\n                                                                     who borrowed     who borrowed       ve principal bor-\n                                                                                      (nearest 1%)     rowed, of those in\n                                                                                                       the first column\n                                                                                                       (nearest $1)\n\nA. Any loan program: Federal Perkins, Federal Sta\ufb00ord Subsidized          501            29.26%              $31,298\n   and Unsubsidized, ins tu onal, state, private loans that your\n   ins tu on is aware of, etc. Include both Federal Direct Student\n   Loans and Federal Family Educa on Loans.\nB. Federal loan programs: Federal Perkins, Federal Sta\ufb00ord Subsi-         476            27.80%              $18,200\n   dized and Unsubsidized. Include both Federal Direct Student\n   Loans and Federal Family Educa on Loans.\nC. Ins tu onal loan programs.                                              6              0.35%              $4,083\n\n\nD. State loan programs.                                                    0              0.00%                 $0\n\n\nE. Private alterna ve loans made by a bank or lender.                      97             5.67%              $72,091\n\n\nAid to Undergraduate Degree-seeking Nonresident Aliens\n(Note: Report numbers and dollar amounts for the same academic year checked in item H1)"
    },
    "H6": {
      "label": ". Indicate your ins tu on\u2019s policy regarding ins tu onal scholarship and grant aid for undergraduate degree-",
      "raw_text": "H6. Indicate your ins tu on\u2019s policy regarding ins tu onal scholarship and grant aid for undergraduate degree-\n    seeking nonresident (interna onal) students:\n\n\n                Ins tu onal need-based scholarship or grant aid is available\n\n\n                Ins tu onal non-need-based scholarship or grant aid is available\n\n\n          X     Ins tu onal scholarship and grant aid is not available\n\nIf ins tu onal aid is available for undergraduate degree-seeking nonresident aliens, provide the number of undergrad-\nuate degree-seeking nonresident aliens who were awarded need-based or non-need-based aid:\n\nAverage dollar amount of ins tu onal financial aid awarded to undergraduate degree-seeking nonresident aliens:\n$_______\n\nTotal dollar amount of ins tu onal financial aid awarded to undergraduate degree-seeking nonresident aliens:\n$_______\n                                 CARNEGIE MELLON UNIVERSITY COMMON DATA SET 2024-2025\n                                                         25"
    },
    "H7": {
      "label": ". Check o\ufb00 all financial aid forms nonresident alien first-year financial aid applicants must submit:",
      "raw_text": "H7. Check o\ufb00 all financial aid forms nonresident alien first-year financial aid applicants must submit:\n\n                 Ins tu on\u2019s own financial aid form\n\n\n                 CSS/Financial Aid PROFILE\n\n\n                 Interna onal Student\u2019s Financial Aid Applica on\n\n\n                 Interna onal Student\u2019s Cer fica on of Finances\n\n\n                 Other:\n\n\nProcess for First-Year/Freshman Students"
    },
    "H8": {
      "label": ". Check o\ufb00 all financial aid forms domes c first-year (freshman) financial aid applicants must submit:",
      "raw_text": "H8. Check o\ufb00 all financial aid forms domes c first-year (freshman) financial aid applicants must submit:\n\n        X     FAFSA\n                                                                         X   Noncustodial PROFILE\n\n              Ins tu on\u2019s own financial aid form\n                                                                             Business/Farm Supplement\n\n\n        X     CSS/Financial Aid PROFILE                                  X   Other: parent and student federal tax returns\n\n\n              State aid form"
    },
    "H9": {
      "label": ". Indicate filing dates for first-year (freshman) students:",
      "raw_text": "H9. Indicate filing dates for first-year (freshman) students:\n\nPriority date for filing required financial aid forms:\n\nDeadline for filing required financial aid forms: February 15\n\nNo deadline for filing required forms (applica ons processed on a rolling basis):"
    },
    "H10": {
      "label": ". Indicate no fica on dates for first-year (freshman) students (answer a or b):",
      "raw_text": "H10. Indicate no fica on dates for first-year (freshman) students (answer a or b):\n\nA. Students no fied on or about (date): April 1\n\nB. Students no fied on a rolling basis:          If yes, star ng date:"
    },
    "H11": {
      "label": ". Indicate reply dates:",
      "raw_text": "H11. Indicate reply dates:\n\nStudents must reply by (date):            5/1      or within                     weeks of no fica on\n\n\n\n                                CARNEGIE MELLON UNIVERSITY COMMON DATA SET 2024-2025\n                                                          26"
    },
    "H12": {
      "label": ". Loans",
      "raw_text": "H12. Loans\n\n             FEDERAL DIRECT STUDENT LOAN PROGRAM (DIRECT LOAN)\n       X       Direct Subsidized Sta\ufb00ord Loans\n\n\n       X       Direct Unsubsidized Sta\ufb00ord Loans\n\n\n       X       Direct PLUS Loans\n\n\n               Federal Perkins Loans\n\n\n              Federal Nursing Loans\n\n\n              State Loans\n\n\n       X      College/university loans from ins tu onal funds\n\n\n              Other (specify):"
    },
    "H13": {
      "label": ". Scholarships and Grants",
      "raw_text": "H13. Scholarships and Grants\n\n             NEED-BASED\n       X       Federal Pell\n\n\n       X       SEOG\n\n\n       X       State scholarships/grants\n\n\n       X       Private scholarships\n\n\n       X       College/university scholarship or grant aid from ins tu onal funds\n\n\n               United Negro College Fund\n\n\n               Federal Nursing Scholarship\n\n\n               Other (specify):\n\n                                 CARNEGIE MELLON UNIVERSITY COMMON DATA SET 2024-2025\n                                                          27"
    },
    "H14": {
      "label": ". Check o\ufb00 criteria used in awarding ins tu onal aid. Check all that apply.",
      "raw_text": "H14. Check o\ufb00 criteria used in awarding ins tu onal aid. Check all that apply.\n\nNon-need Need-based\n\n    X            X       Academics\n\n                         Alumni a\ufb03lia on\n\n    X            X       Art\n\n                         Athle cs\n\n                         Job skills\n\n    X                    ROTC\n\n    X            X       Leadership\n\n                         Minority status\n\n    X            X       Music/drama\n\n                         Religious a\ufb03lia on\n\n    X            X       State/district residency"
    },
    "H15": {
      "label": ". If your ins tu on has recently implemented any major financial aid policy, program, or ini a ve to make your",
      "raw_text": "H15. If your ins tu on has recently implemented any major financial aid policy, program, or ini a ve to make your\n     ins tu on more a\ufb00ordable to incoming students such as replacing loans with grants, or waiving costs for\n     families below a certain income level please provide details below:\n\n\n\n\n                               CARNEGIE MELLON UNIVERSITY COMMON DATA SET 2024-2025\n                                                        28"
    }
  },
  "I": {
    "_section_label": "I.? INSTRUCTIONAL FACULTY AND CLASS SIZE",
    "I1": {
      "label": ". Report number of instruc onal faculty members in each category for Fall 2024. Include faculty who are on your",
      "raw_text": "I1. Report number of instruc onal faculty members in each category for Fall 2024. Include faculty who are on your\n    ins tu on's payroll on the census date your ins tu on uses for IPEDS/AAUP.\n\nThe following defini on of instruc onal faculty is used by the American Associa on of University Professors (AAUP) in\nits annual Faculty Compensa on Survey (the part- me defini ons are not used by AAUP). Instruc onal Faculty is de-\nfined as those members of the instruc onal-research sta\ufb00 whose major regular assignment is instruc on, including\nthose with released me for research. Use the direc ons below to determine inclusions and exclusions:\n\n                                                                                      Full- me Part- me\nA. Instruc onal faculty in preclinical and clinical medicine, faculty who are not paid Exclude      Include only if they\n    (e.g., those who donate their services or are in the military), or research-only                teach one or more non\n    faculty, post-doctoral fellows, or pre-doctoral fellows                                         -clinical credit courses\nB. Administra ve o\ufb03cers with tles such as dean of students, librarian, coach, and Exclude           Include if they teach\n   the like, even though they may devote part of their me to classroom instruc-                     one or more non-\n    on and may have faculty status                                                                  clinical credit courses\nC. Other administrators/sta\ufb00 who teach one or more non-clinical credit courses        Exclude       Include\n   even though they do not have faculty status\nD. Undergraduate or graduate students who assist in the instruc on of courses,        Exclude       Exclude\n   but have tles such as teaching assistant, teaching fellow, and the like\nE. Faculty on sabba cal or leave with pay                                             Include       Exclude\nF. Faculty on leave without pay                                                       Exclude       Exclude\nG. Replacement faculty for faculty on sabba cal leave or leave with pay               Exclude       Include\n\nFull- me instruc onal faculty\n Faculty employed on a full- me basis for instruc on (including those with released me for research).\n\nPart- me instruc onal faculty\n Adjuncts and other instructors being paid solely for part- me classroom instruc on. Also includes full- me faculty\n teaching less than two semesters, three quarters, two trimesters, or two four-month sessions. Employees who are not\n considered full- me instruc onal faculty but who teach one or more non-clinical credit courses may be counted as\n part- me faculty.\n\nMinority faculty\n Includes faculty who designate themselves as Black, non-Hispanic; American Indian or Alaska Na ve; Asian, Na ve\nHawaiian or other Pacific Islander, or Hispanic.\n\nDoctorate\n Includes such degrees as Doctor of Philosophy, Doctor of Educa on, Doctor of Juridical Science, and Doctor of Public\n Health in any field such as arts, sciences, educa on, engineering, business, and public administra on. Also includes\n terminal degrees formerly designated as \u201cfirst professional,\u201d including den stry (DDS or DMD), medicine (MD), op-\n tometry (OD), osteopathic medicine (DO), pharmacy (DPharm or BPharm), podiatric medicine (DPM), veterinary medi-\n cine (DVM), chiroprac c (DC or DCM), or law (JD).\n\nTerminal degree\n The highest degree in a field: example, M. Arch (in architecture) and MFA (master of fine arts).\n\n\n                              CARNEGIE MELLON UNIVERSITY COMMON DATA SET 2024-2025\n                                                       29"
    },
    "I2": {
      "label": ". Student to Faculty Ra o",
      "raw_text": "  I2. Student to Faculty Ra o\n Report the Fall 2024 ra o of full- me equivalent students (full- me plus 1/3 part- me) to full- me equivalent instruc-\n   onal faculty (full- me plus 1/3 part- me). In the ra o calcula ons, exclude both faculty and students in stand-alone\n graduate or professional programs such as medicine, law, veterinary, den stry, social work, business, or public health\n in which faculty teach virtually only graduate-level students. Do not count undergraduate or graduate student teaching\n assistants as faculty.\n\n Fall 2024 Student to Faculty ra o: 6     to 1 (based on 7,498 students and _1,200 faculty).\n\n\n\n\n                                CARNEGIE MELLON UNIVERSITY COMMON DATA SET 2024-2025\n                                                         30"
    },
    "I3": {
      "label": ". Undergraduate Class Size",
      "raw_text": "I3. Undergraduate Class Size\nIn the table below, please use the following defini ons to report informa on about the size of classes and class sec-\n  ons o\ufb00ered in the Fall 2024 term.\n\nClass Sec ons\n A class sec on is an organized course o\ufb00ered for credit, iden fied by discipline and number, mee ng at a stated me\n or mes in a classroom or similar se ng, and not a subsec on such as a laboratory or discussion sec on. Undergradu-\n ate class sec ons are defined as any sec ons in which at least one degree-seeking undergraduate student is enrolled\n for credit. Exclude distance learning classes and noncredit classes and individual instruc on such as disserta on or\n thesis research, music instruc on, or one-to-one readings. Exclude students in independent study, co-opera ve pro-\n grams, internships, foreign language taped tutor sessions, prac cums, and all students in on-on-one classes. Each class\n sec on should be counted only once and should not be duplicated because of course catalog cross-lis ngs.\n\nClass Subsec ons\n A class subsec on includes any subsec on of a course, such as a laboratory, recita on, and discussion subsec ons\n that are supplementary in nature and are scheduled to meet separately from the lecture por on of the course. Under-\n graduate subsec ons are defined as any subsec ons of courses in which degree-seeking undergraduate students en-\n rolled for credit. As above, exclude noncredit classes and individual instruc on such as disserta on or thesis research,\n music instruc on, or one-to-one readings. Each class subsec on should be counted only once and should not be dupli-\n cated because of cross-lis ngs.\n\nUsing the above defini ons, please report for each of the following class-size intervals the number of class sec ons and\nclass subsec ons o\ufb00ered in Fall 2024. For example, a lecture class with 800 students who met at another me in 40 sep-\narate labs with 20 students should be counted once in the \u201c100+\u201d column in the class sec on column and 40 mes un-\nder the \u201c20-20\u201d column of the class subsec ons table.\n\n\n                        Number of Class Sec ons with Undergraduates Enrolled\n\n                                Undergraduate Class Size (provide numbers)\n                          2-9        10-19      20-29      30-39      40-49     50-99     100+      Total\n  CLASS SECTIONS          646         575        209        90          74       132       70        1797\nCLASS SUBSECTIONS         67          204        240        113         17        8         0        649\n\n\n\n\n                                CARNEGIE MELLON UNIVERSITY COMMON DATA SET 2024-2025\n                                                         31"
    }
  },
  "J": {
    "_section_label": "J.? (?:DEGREES?|DISCIPLINARY) (?:CONFERRED|AREAS?)"
  }
}